entity_embeddings/__init__.py
entity_embeddings/config.py
entity_embeddings/embedder.py
entity_embeddings/network/__init__.py
entity_embeddings/network/assembler.py
entity_embeddings/network/network.py
entity_embeddings/processor/__init__.py
entity_embeddings/processor/processor.py
entity_embeddings/processor/target_type.py
entity_embeddings/util/__init__.py
entity_embeddings/util/dataframe_utils.py
entity_embeddings/util/model_utils.py
entity_embeddings/util/preprocessing_utils.py
entity_embeddings/util/processor_utils.py
entity_embeddings/util/validation_utils.py
entity_embeddings/util/visualization_utils.py
tests/__init__.py
tests/test_assembler.py
tests/test_config.py
tests/test_dataframe_utils.py
tests/test_embedder.py
tests/test_network.py
tests/test_preprocessing_utils.py
tests/test_processor_utils.py
tests/test_validation_utils.py
tests/test_visualization_utils.py
entity_embeddings_categorical-0.6.7.dist-info/LICENSE.md
entity_embeddings_categorical-0.6.7.dist-info/METADATA
entity_embeddings_categorical-0.6.7.dist-info/WHEEL
entity_embeddings_categorical-0.6.7.dist-info/top_level.txt
entity_embeddings_categorical-0.6.7.dist-info/RECORD
