Metadata-Version: 2.1
Name: entity-embeddings-categorical
Version: 0.6.7
Summary: UNKNOWN
Home-page: https://github.com/bresan/entity_embeddings_categorical
Author: Rodrigo Bresan
Author-email: 
License: BSD-3-Clause
Platform: UNKNOWN
Classifier: Programming Language :: Python :: 3.6
Requires-Dist: absl-py (==0.7.0)
Requires-Dist: alabaster (==0.7.12)
Requires-Dist: astor (==0.7.1)
Requires-Dist: atomicwrites (==1.3.0)
Requires-Dist: attrs (==19.1.0)
Requires-Dist: Babel (==2.6.0)
Requires-Dist: bleach (==1.5.0)
Requires-Dist: certifi (==2018.11.29)
Requires-Dist: chardet (==3.0.4)
Requires-Dist: cycler (==0.10.0)
Requires-Dist: docutils (==0.14)
Requires-Dist: gast (==0.2.2)
Requires-Dist: grpcio (==1.19.0)
Requires-Dist: h5py (==2.9.0)
Requires-Dist: html5lib (==0.9999999)
Requires-Dist: idna (==2.8)
Requires-Dist: imagesize (==1.1.0)
Requires-Dist: Jinja2 (==2.10)
Requires-Dist: Keras (==2.2.4)
Requires-Dist: Keras-Applications (==1.0.7)
Requires-Dist: Keras-Preprocessing (==1.0.9)
Requires-Dist: kiwisolver (==1.0.1)
Requires-Dist: Markdown (==3.0.1)
Requires-Dist: MarkupSafe (==1.1.1)
Requires-Dist: matplotlib (==3.0.3)
Requires-Dist: mock (==2.0.0)
Requires-Dist: more-itertools (==6.0.0)
Requires-Dist: numpy (==1.16.2)
Requires-Dist: packaging (==19.0)
Requires-Dist: pandas (==0.24.1)
Requires-Dist: pbr (==5.1.3)
Requires-Dist: pip-review (==1.0)
Requires-Dist: pluggy (==0.9.0)
Requires-Dist: protobuf (==3.7.0)
Requires-Dist: py (==1.8.0)
Requires-Dist: Pygments (==2.3.1)
Requires-Dist: pyparsing (==2.3.1)
Requires-Dist: pytest (==4.3.0)
Requires-Dist: python-dateutil (==2.8.0)
Requires-Dist: pytz (==2018.9)
Requires-Dist: PyYAML (==3.13)
Requires-Dist: requests (==2.21.0)
Requires-Dist: scikit-learn (==0.20.3)
Requires-Dist: scipy (==1.2.1)
Requires-Dist: six (==1.12.0)
Requires-Dist: sklearn (==0.0)
Requires-Dist: snowballstemmer (==1.2.1)
Requires-Dist: Sphinx (==1.8.4)
Requires-Dist: sphinx-rtd-theme (==0.4.3)
Requires-Dist: sphinxcontrib-websupport (==1.1.0)
Requires-Dist: tensorboard (==1.13.1)
Requires-Dist: tensorflow (==1.5.0)
Requires-Dist: tensorflow-estimator (==1.13.0)
Requires-Dist: tensorflow-tensorboard (==1.5.1)
Requires-Dist: termcolor (==1.1.0)
Requires-Dist: urllib3 (==1.24.1)
Requires-Dist: webencodings (==0.5.1)
Requires-Dist: Werkzeug (==0.14.1)
